mzcli/__init__.py
mzcli/__main__.py
mzcli/completion_refresher.py
mzcli/config.py
mzcli/key_bindings.py
mzcli/magic.py
mzcli/main.py
mzcli/mzclirc
mzcli/pgbuffer.py
mzcli/pgcompleter.py
mzcli/pgexecute.py
mzcli/pgstyle.py
mzcli/pgtoolbar.py
mzcli/packages/__init__.py
mzcli/packages/prioritization.py
mzcli/packages/prompt_utils.py
mzcli/packages/sqlcompletion.py
mzcli/packages/parseutils/__init__.py
mzcli/packages/parseutils/ctes.py
mzcli/packages/parseutils/meta.py
mzcli/packages/parseutils/tables.py
mzcli/packages/parseutils/utils.py
mzcli/packages/pgliterals/__init__.py
mzcli/packages/pgliterals/main.py
mzcli/packages/pgliterals/pgliterals.json
mzcli-3.0.0.dist-info/AUTHORS
mzcli-3.0.0.dist-info/LICENSE.txt
mzcli-3.0.0.dist-info/METADATA
mzcli-3.0.0.dist-info/WHEEL
mzcli-3.0.0.dist-info/entry_points.txt
mzcli-3.0.0.dist-info/top_level.txt
mzcli-3.0.0.dist-info/RECORD
