Metadata-Version: 2.1
Name: mzcli
Version: 3.0.0
Summary: CLI for the Materialize streaming database. With auto-completion and syntax highlighting.
Home-page: https://materialize.io
Author: Pgcli Core Team + The Materialize developers
Author-email: bugs@materialize.io
License: BSD
Platform: UNKNOWN
Classifier: Intended Audience :: Developers
Classifier: License :: OSI Approved :: BSD License
Classifier: Operating System :: Unix
Classifier: Programming Language :: Python
Classifier: Programming Language :: Python :: 3
Classifier: Programming Language :: Python :: 3.6
Classifier: Programming Language :: Python :: 3.7
Classifier: Programming Language :: Python :: 3.8
Classifier: Programming Language :: SQL
Classifier: Topic :: Database
Classifier: Topic :: Database :: Front-Ends
Classifier: Topic :: Software Development
Classifier: Topic :: Software Development :: Libraries :: Python Modules
Requires-Python: >=3.6
Requires-Dist: pgspecial (>=1.11.8)
Requires-Dist: click (>=4.1)
Requires-Dist: Pygments (>=2.0)
Requires-Dist: prompt-toolkit (<4.0.0,>=2.0.6)
Requires-Dist: psycopg2 (>=2.8)
Requires-Dist: sqlparse (<0.4,>=0.3.0)
Requires-Dist: configobj (>=5.0.6)
Requires-Dist: pendulum (>=2.1.0)
Requires-Dist: cli-helpers[styles] (>=2.0.0)
Requires-Dist: setproctitle (>=1.1.9)
Provides-Extra: keyring
Requires-Dist: keyring (>=12.2.0) ; extra == 'keyring'
